pipe/__init__.py
pipe/core/__init__.py
pipe/core/base.py
pipe/core/decorators.py
pipe/core/exceptions.py
pipe/generics/__init__.py
pipe/generics/helpers.py
pipe/generics/db/__init__.py
pipe/generics/db/exceptions.py
pipe/generics/db/orator_orm/__init__.py
pipe/generics/db/orator_orm/extract.py
pipe/generics/db/orator_orm/load.py
pipe/generics/db/orator_orm/mixins.py
pipe/generics/template/__init__.py
pipe/generics/template/transform.py
pipe/server/__init__.py
pipe/server/pipe.py
pipe/server/wrappers.py
pipe/server/http/__init__.py
pipe/server/http/exceptions.py
pipe/server/http/extract.py
pipe/server/http/load.py
pipe/server/http/transform.py
pipe_framework-0.1.0a0.dist-info/LICENSE
pipe_framework-0.1.0a0.dist-info/METADATA
pipe_framework-0.1.0a0.dist-info/WHEEL
pipe_framework-0.1.0a0.dist-info/top_level.txt
pipe_framework-0.1.0a0.dist-info/RECORD
