Metadata-Version: 2.1
Name: pipe-framework
Version: 0.1.0a0
Summary: Data oriented web framework
Home-page: https://github.com/jellyfish-tech/pipe-framework
Author: NeZanyat
Author-email: rlatyshenko@gmail.com
License: UNKNOWN
Platform: UNKNOWN
Classifier: Programming Language :: Python :: 3
Classifier: License :: OSI Approved :: MIT License
Classifier: Operating System :: OS Independent
Requires-Python: >=3.6
Requires-Dist: werkzeug (==1.0.1)
Requires-Dist: Jinja2 (==2.11.2)
Requires-Dist: frozendict (==1.2)
Requires-Dist: orator (==0.9.9)
Requires-Dist: rich (==5.2.1)
Requires-Dist: valideer (==0.4.2)
